gsapme/__init__.py
gsapme/analysis.py
gsapme/covariance.py
gsapme/models.py
gsapme/simulation.py
gsapme-0.1.3.dist-info/METADATA
gsapme-0.1.3.dist-info/WHEEL
gsapme-0.1.3.dist-info/RECORD
